bytewax/clickhouse/__init__.py
bytewax/clickhouse/operators.py
bytewax/clickhouse/py.typed
bytewax_clickhouse-0.0.1.dist-info/LICENSE.md
bytewax_clickhouse-0.0.1.dist-info/METADATA
bytewax_clickhouse-0.0.1.dist-info/WHEEL
bytewax_clickhouse-0.0.1.dist-info/top_level.txt
bytewax_clickhouse-0.0.1.dist-info/RECORD
