Metadata-Version: 2.1
Name: bytewax-clickhouse
Version: 0.0.1
Summary: Clickhouse sink connector for bytewax
Author-email: "Bytewax, Inc." <info@bytewax.io>
License: # Software License Agreement
Project-URL: Homepage, https://github.com/bytewax/bytewax-clickhouse
Project-URL: Bug Reports, https://github.com/bytewax/bytewax-clickhouse/issues/new
Project-URL: Source, https://github.com/bytewax/bytewax-clickhouse/
Keywords: bytewax,streaming,operator
Classifier: Development Status :: 4 - Beta
Classifier: Intended Audience :: Developers
Classifier: Programming Language :: Python :: 3
Classifier: Programming Language :: Python :: 3.9
Classifier: Programming Language :: Python :: 3.10
Classifier: Programming Language :: Python :: 3.11
Classifier: Programming Language :: Python :: 3.12
Classifier: Programming Language :: Python :: 3 :: Only
Requires-Python: >=3.9
License-File: LICENSE.md
Requires-Dist: clickhouse-connect==0.7.16
Requires-Dist: bytewax>=0.21
Requires-Dist: pyarrow==16.1.0
